{
  "build": {
    "content": [
      {
        "files": ["breadcrumb/toc.yml"]
      },
      {
        "files": [
          "**/*.md",
          "**/*.yml"
        ],
        "exclude": [
          "**/obj/**",
          "**/includes/**",
          "_themes/**",
          "_themes.pdf/**",
          "**/docfx.json",
          "_repo.en-us/**",
          "README.md",
          "LICENSE",
          "LICENSE-CODE",
          "ThirdPartyNotices.md"
        ]
      }
    ],
    "resource": [
      {
        "files": [
          "**/*.png",
          "**/*.jpg"
        ],
        "exclude": [
          "**/obj/**",
          "**/includes/**",
          "_themes/**",
          "_themes.pdf/**",
          "**/docfx.json",
          "_repo.en-us/**"
        ]
      }
    ],
    "overwrite": [],
    "externalReference": [],
    "globalMetadata": {
      "breadcrumb_path": "/windows/windows-app-sdk/api/win32/breadcrumb/toc.json",
      "extendBreadcrumb": true,
      "feedback_system": "GitHub",
      "feedback_github_repo": "MicrosoftDocs/winapps-win32-api",
      "feedback_product_url": "https://github.com/microsoft/ProjectReunion/issues",
      "uhfHeaderId": "MSDocsHeader-WinDevCenter",
      "titleSuffix": "Windows App SDK",
      "ms.prod": "reunion",
      "ms.technology": "reunion-reference",
      "ms.author": "jken",
      "author": "GrantMeStrength"
    },
    "fileMetadata": {
      "author": {
        "_bootstrap/*.md": "stevewhims",
        "_dwritecore/*.md": "stevewhims",
        "_dynamicdependency/*.md": "stevewhims",
        "_licensing/*.md": "stevewhims",
        "_mrtcore/*.md": "stevewhims",
        "_uiinterop/*.md": "jwmsft",
        "_winuicominterop/*.md": "Karl-Bridge-Microsoft",
        "dwrite/*.md": "stevewhims",
        "dwrite_3/*.md": "stevewhims",
        "dwritecore/*.md": "stevewhims",
        "mddbootstrap/*.md": "stevewhims",
        "microsoft.ui.composition.interop/*.md": "jwmsft",
        "microsoft.ui.dispatching.interop/*.md": "Karl-Bridge-Microsoft",
        "microsoft.ui.input.inputcursor.interop/*.md": "Karl-Bridge-Microsoft",
        "microsoft.ui.input.inputpretranslatesource.interop/*.md": "Karl-Bridge-Microsoft",
        "microsoft.ui.interop/*.md": "jwmsft",
        "microsoft.ui.xaml.hosting.desktopwindowxamlsource/*.md": "Karl-Bridge-Microsoft",
        "microsoft.ui.xaml.hosting.referencetracker/*.md": "Karl-Bridge-Microsoft",
        "microsoft.ui.xaml.media.dxinterop/*.md": "Karl-Bridge-Microsoft",
        "microsoft.ui.xaml.window/*.md": "Karl-Bridge-Microsoft",
        "mrm/*.md": "Karl-Bridge-Microsoft",
        "msixdynamicdependency/*.md": "stevewhims",
        "security.accesscontrol/*.md": "stevewhims",
        "windowsappruntime-licensing/*.md": "stevewhims",
        "winrt-microsoft.ui.interop/*.md": "jwmsft"
      },
      "ms.author":
      {
        "_bootstrap/*.md": "stwhi",
        "_dwritecore/*.md": "stwhi",
        "_dynamicdependency/*.md": "stwhi",
        "_licensing/*.md": "stwhi",
        "_mrtcore/*.md": "stwhi",
        "_uiinterop/*.md": "jimwalk",
        "_winuicominterop/*.md": "kbridge",
        "dwrite/*.md": "stwhi",
        "dwrite_3/*.md": "stwhi",
        "dwritecore/*.md": "stwhi",
        "mddbootstrap/*.md": "stwhi",
        "microsoft.ui.composition.interop/*.md": "jimwalk",
        "microsoft.ui.dispatching.interop/*.md": "kbridge",
        "microsoft.ui.input.inputcursor.interop/*.md": "kbridge",
        "microsoft.ui.input.inputpretranslatesource.interop/*.md": "kbridge",
        "microsoft.ui.interop/*.md": "jimwalk",
        "microsoft.ui.xaml.hosting.desktopwindowxamlsource/*.md": "kbridge",
        "microsoft.ui.xaml.hosting.referencetracker/*.md": "kbridge",
        "microsoft.ui.xaml.media.dxinterop/*.md": "kbridge",
        "microsoft.ui.xaml.window/*.md": "kbridge",
        "mrm/*.md": "kbridge",
        "msixdynamicdependency/*.md": "stwhi",
        "security.accesscontrol/*.md": "stwhi",
        "windowsappruntime-licensing/*.md": "stwhi",
        "winrt-microsoft.ui.interop/*.md": "jimwalk"
      }
    },
    "template": [],
    "dest": "winapps-win32-api-build",
    "markdownEngineName": "markdig"
  }
}